cpu/lsu/sp/sp.v
module sp
(
    input d, //1 = decrement; 0 = increment;
    input en,

    input clk, rst,

    output reg[15:0] q
);

    reg[14:0] sp;

    initial
    begin
        sp <= 15'h7FFF;
    end

    always @(posedge clk)
    begin
        if (rst)
        begin
            sp <= 15'h7FFF;
            q <= 15'h7FFF;
        end

        else
        begin
            if (en)
            begin
                if (d)
                    sp--;
                else 
                    sp++;
            end

            q <= { 1'b0, sp };
        end
    end

endmodule

src/lsu/sp/sp_tb.v
`timescale 1ns / 100ps
`include "sp.v"

module sp_tb;
    reg d = 0, en = 0;
    reg clk = 0, rst = 0;

    wire[15:0] q;

always #1 clk = !clk;

initial $dumpfile("sp_tb.vcd");
initial $dumpvars(0, sp_tb);

sp s
(
    .d(d),
    .en(en),
    .clk(clk),
    .rst(rst),
    .q(q)
);

initial
begin
    #4 d = 1; en = 1;
    #5
    #5 en = 0;
    #5 
    #5 d = 0; en = 1;
    #5
    #5
    #1 d = 1;
    #6 d = 0;
    #5 rst = 1;
    #5 rst = 0; d = 0;
    #5 en = 1;
    #5 $finish;
end

endmodule

src/lsu/sp/sp_tb.vcd
$date
	Fri Sep  9 16:05:18 2022
$end
$version
	Icarus Verilog
$end
$timescale
	100ps
$end
$scope module sp_tb $end
$var wire 16 ! q [15:0] $end
$var reg 1 " clk $end
$var reg 1 # d $end
$var reg 1 $ en $end
$var reg 1 % rst $end
$scope module s $end
$var wire 1 " clk $end
$var wire 1 # d $end
$var wire 1 $ en $end
$var wire 1 % rst $end
$var reg 16 & q [15:0] $end
$var reg 15 ' sp [14:0] $end
$upscope $end
$upscope $end
$enddefinitions $end
#0
$dumpvars
b111111111111111 '
bx &
0%
0$
0#
0"
bx !
$end
#10
b111111111111111 !
b111111111111111 &
1"
#20
0"
#30
1"
#40
0"
1$
1#
#50
b111111111111110 !
b111111111111110 &
b111111111111110 '
1"
#60
0"
#70
b111111111111101 !
b111111111111101 &
b111111111111101 '
1"
#80
0"
#90
b111111111111100 !
b111111111111100 &
b111111111111100 '
1"
#100
0"
#110
b111111111111011 !
b111111111111011 &
b111111111111011 '
1"
#120
0"
#130
b111111111111010 !
b111111111111010 &
b111111111111010 '
1"
#140
0"
0$
#150
1"
#160
0"
#170
1"
#180
0"
#190
1"
#200
0"
#210
1"
#220
0"
#230
1"
#240
0"
1$
0#
#250
b111111111111011 !
b111111111111011 &
b111111111111011 '
1"
#260
0"
#270
b111111111111100 !
b111111111111100 &
b111111111111100 '
1"
#280
0"
#290
b111111111111101 !
b111111111111101 &
b111111111111101 '
1"
#300
0"
#310
b111111111111110 !
b111111111111110 &
b111111111111110 '
1"
#320
0"
#330
b111111111111111 !
b111111111111111 &
b111111111111111 '
1"
#340
0"
#350
b111111111111110 !
b111111111111110 &
b111111111111110 '
1"
1#
#360
0"
#370
b111111111111101 !
b111111111111101 &
b111111111111101 '
1"
#380
0"
#390
b111111111111100 !
b111111111111100 &
b111111111111100 '
1"
#400
0"
#410
b111111111111101 !
b111111111111101 &
b111111111111101 '
1"
0#
#420
0"
#430
b111111111111110 !
b111111111111110 &
b111111111111110 '
1"
#440
0"
#450
b111111111111111 !
b111111111111111 &
b111111111111111 '
1"
#460
0"
1%
#470
1"
#480
0"
#490
1"
#500
0"
#510
b0 !
b0 &
b0 '
1"
0%
#520
0"
#530
b1 !
b1 &
b1 '
1"
#540
0"
#550
b10 !
b10 &
b10 '
1"
#560
0"
#570
b11 !
b11 &
b11 '
1"
#580
0"
#590
b100 !
b100 &
b100 '
1"
#600
0"
#610
b101 !
b101 &
b101 '
1"
