src/lsu/rom/rom.v
module rom
(
	input [15:0] a,

	input re,
	input clk,

	output reg[7:0] q0, q1, q2, q3
);
	localparam SIZE = 32768;
	localparam READ_SIZE = 3;

	localparam WRITE_FILE = 1;

	wire[15:0] ac = { 16{ (a >= SIZE) } } & (a - SIZE);

	reg[7:0] m[0:SIZE-1];

	initial
	begin
		$readmemh("/Users/connor/desktop/cpu-design/test.o", m);

		if (WRITE_FILE)
			for (integer i = 0; i < 32768; i++)
				$display("%d: %h", i, m[i]);
	end

	always @(posedge clk)
	begin
		if (a >= SIZE && a <= (16'hFFFF - READ_SIZE) && re)
		begin
			q0 <= m[ac + 0];
			q1 <= m[ac + 1];
			q2 <= m[ac + 2];
			q3 <= m[ac + 3];
		end

		else
		begin
			q0 <= 8'bz;
			q1 <= 8'bz;
			q2 <= 8'bz;
			q3 <= 8'bz;
		end
	end
endmodule

src/lsu/rom/rom_tb.v
`timescale 1ns / 100ps
`include "rom.v"

module rom_tb;
    reg clk = 0;
    reg re = 1;

    reg[15:0] a = 0;

    wire[7:0] q0, q1, q2, q3;

always #1 clk = !clk;

initial $dumpfile("rom_tb.vcd");
initial $dumpvars(0, rom_tb);

rom r
(
   .a(a),
   .re(re),
   .clk(clk),
   .q0(q0),
   .q1(q1),
   .q2(q2),
   .q3(q3)
);

initial 
begin
    #5 re = 1;
    #5 a = 32768;
    #5 a = 32769;
    #5 a = 40000;
    #5 re = 0;
    #5 a = 32768;
    #5 a = 10;
    #5 a = 65537;
    #5 re = 1;
    #5 a = 32769;
    #5 a = 10;
    #5 $finish;
end

endmodule

src/lsu/rom/rom_tb.vcd
$date
	Mon Sep  5 21:18:09 2022
$end
$version
	Icarus Verilog
$end
$timescale
	100ps
$end
$scope module rom_tb $end
$var wire 8 ! q3 [7:0] $end
$var wire 8 " q2 [7:0] $end
$var wire 8 # q1 [7:0] $end
$var wire 8 $ q0 [7:0] $end
$var reg 16 % a [15:0] $end
$var reg 1 & clk $end
$var reg 1 ' re $end
$scope module r $end
$var wire 16 ( a [15:0] $end
$var wire 1 & clk $end
$var wire 1 ' re $end
$var wire 16 ) ac [15:0] $end
$var reg 8 * q0 [7:0] $end
$var reg 8 + q1 [7:0] $end
$var reg 8 , q2 [7:0] $end
$var reg 8 - q3 [7:0] $end
$scope begin $ivl_for_loop0 $end
$var integer 32 . i [31:0] $end
$upscope $end
$upscope $end
$upscope $end
$enddefinitions $end
#0
$dumpvars
b1000000000000000 .
bx -
bx ,
bx +
bx *
b0 )
b0 (
1'
0&
b0 %
bx $
bx #
bx "
bx !
$end
#10
bz !
bz -
bz "
bz ,
bz #
bz +
bz $
bz *
1&
#20
0&
#30
1&
#40
0&
#50
1&
#60
0&
#70
1&
#80
0&
#90
1&
#100
0&
b1000000000000000 %
b1000000000000000 (
#110
b1 !
b1 -
b1100000 "
b1100000 ,
b101 #
b101 +
b1011110 $
b1011110 *
1&
#120
0&
#130
1&
#140
0&
#150
b1 )
1&
b1000000000000001 %
b1000000000000001 (
#160
0&
#170
b10 !
b10 -
b1 "
b1 ,
b1100000 #
b1100000 +
b101 $
b101 *
1&
#180
0&
#190
1&
#200
b1110001000000 )
0&
b1001110001000000 %
b1001110001000000 (
#210
b0 !
b0 -
b0 "
b0 ,
b0 #
b0 +
b0 $
b0 *
1&
#220
0&
#230
1&
#240
0&
#250
bz !
bz -
bz "
bz ,
bz #
bz +
bz $
bz *
1&
0'
#260
0&
#270
1&
#280
0&
#290
1&
#300
b0 )
0&
b1000000000000000 %
b1000000000000000 (
#310
1&
#320
0&
#330
1&
#340
0&
#350
1&
b1010 %
b1010 (
#360
0&
#370
1&
#380
0&
#390
1&
#400
0&
b1 %
b1 (
#410
1&
#420
0&
#430
1&
#440
0&
#450
1&
1'
#460
0&
#470
1&
#480
0&
#490
1&
#500
b1 )
0&
b1000000000000001 %
b1000000000000001 (
#510
b10 !
b10 -
b1 "
b1 ,
b1100000 #
b1100000 +
b101 $
b101 *
1&
#520
0&
#530
1&
#540
0&
#550
bz !
bz -
bz "
bz ,
bz #
bz +
bz $
bz *
b0 )
1&
b1010 %
b1010 (
