cpu/adu/adu.v
module adu
(
    input[15:0] a,

    input we,
    input rl, rh,
    input clk, rst,

    input oe,

    output reg[7:0] q
);
    reg[15:0] tmp;

    initial
    begin
        tmp <= 16'h0000;
        q <= 8'bz;
    end

    always @(posedge clk)
    begin
        if (rst)
        begin
            tmp = 16'h0000;

            if (oe)
                q = tmp;
            else
                q = 16'bz;
        end

        else
        begin
            if (we)
                tmp = a;

            if (rl)
            begin
                if (oe)
                    q = tmp[7:0];
                else
                    q = 8'bz;
            end

            else if (rh)
            begin
                if (oe)
                    q = tmp[15:8];
                else 
                    q = 8'bz;
            end

            else
                q = 8'bz;
        end
    end

endmodule

cpu/adu/adu_tb.v
`timescale 1ns / 100ps
`include "adu.v"

module adu_tb;
    reg[15:0] a = 0;
    
    reg we = 0;
    reg rl = 0, rh = 0;
    reg clk = 0, rst = 0;

    reg oe = 0;

    wire[7:0] q;

always #1 clk = !clk;

initial $dumpfile("adu_tb.vcd");
initial $dumpvars(0, adu_tb);

adu du
(
    .a(a),
    .we(we),
    .rl(rl),
    .rh(rh),
    .clk(clk),
    .rst(rst),
    .oe(oe),
    .q(q)
);

initial
begin
    #5 a = 31246; we = 1; oe = 1;
    #5 we = 0; rl = 1;
    #5 rl = 0; rh = 1;
    #1 oe = 0;
    #5 a = 20000; we = 1;
    #5 oe = 1;
    #5 we = 0; rh = 1;
    #5 oe = 0;
    #5 rh = 0; rl = 1;
    #5 oe = 1;
    #5 rst = 1;
    #5 rst = 0;
    #5 $finish;
end

endmodule

cpu/adu/adu_tb.vcd
$date
	Mon Sep 12 19:12:01 2022
$end
$version
	Icarus Verilog
$end
$timescale
	100ps
$end
$scope module adu_tb $end
$var wire 8 ! q [7:0] $end
$var reg 16 " a [15:0] $end
$var reg 1 # clk $end
$var reg 1 $ oe $end
$var reg 1 % rh $end
$var reg 1 & rl $end
$var reg 1 ' rst $end
$var reg 1 ( we $end
$scope module du $end
$var wire 16 ) a [15:0] $end
$var wire 1 # clk $end
$var wire 1 $ oe $end
$var wire 1 % rh $end
$var wire 1 & rl $end
$var wire 1 ' rst $end
$var wire 1 ( we $end
$var reg 8 * q [7:0] $end
$var reg 16 + tmp [15:0] $end
$upscope $end
$upscope $end
$enddefinitions $end
#0
$dumpvars
b0 +
bz *
b0 )
0(
0'
0&
0%
0$
0#
b0 "
bz !
$end
#10
1#
#20
0#
#30
1#
#40
0#
#50
b111101000001110 +
1#
1$
1(
b111101000001110 "
b111101000001110 )
#60
0#
#70
1#
#80
0#
#90
1#
#100
0#
1&
0(
#110
b1110 !
b1110 *
1#
#120
0#
#130
1#
#140
0#
#150
b1111010 !
b1111010 *
1#
1%
0&
#160
0#
0$
#170
bz !
bz *
1#
#180
0#
#190
1#
#200
0#
#210
b100111000100000 +
1#
1(
b100111000100000 "
b100111000100000 )
#220
0#
#230
1#
#240
0#
#250
1#
#260
0#
1$
#270
b1001110 !
b1001110 *
1#
#280
0#
#290
1#
#300
0#
#310
1#
0(
#320
0#
#330
1#
#340
0#
#350
1#
#360
0#
0$
#370
bz !
bz *
1#
#380
0#
#390
1#
#400
0#
#410
1#
1&
0%
#420
0#
#430
1#
#440
0#
#450
1#
#460
0#
1$
#470
b100000 !
b100000 *
1#
#480
0#
#490
1#
#500
0#
#510
b0 !
b0 *
b0 +
1#
1'
#520
0#
#530
1#
#540
0#
#550
1#
#560
0#
0'
