src/msc/reg/register.v
module register
(
    input[7:0] d, 
    
    input en,
    input clk,

    output reg[7:0] q
);
    always @(posedge clk)
    begin
        if (en)
            q <= d;
    end
endmodule

module register_rst
(
    input[7:0] d,
    
    input en,
    input clk, rst,

    output reg[7:0] q
);
    always @(posedge clk)
    begin
        if (en && !rst)
            q <= d;
        else if (rst)
            q <= 8'h00;
    end
endmodule

src/msc/reg/register_tb.v
`timescale 1ns / 100ps
`include "register.v"

module register_tb;

reg clk = 0, rst = 0;
reg en = 1;

reg[7:0] d;
wire[7:0] q;

always #1 clk = !clk;

initial $dumpfile("register_tb.vcd");
initial $dumpvars(0, register_tb);

register_rst r
(
    .d(d),
    .en(en),
    .clk(clk),
    .rst(rst),
    .q(q)
);

initial
begin
    #5 d = 31;
    #5 d = 127;
    #5 en = 0;
    #5 d = 12;
    #5 en = 1; d = 100; rst = 1;
    #5 en = 0; rst = 0;
    #5 $finish;
end
endmodule

src/msc/reg/register_tb.vcd
$date
	Mon Sep  5 18:47:00 2022
$end
$version
	Icarus Verilog
$end
$timescale
	100ps
$end
$scope module register_tb $end
$var wire 8 ! q [7:0] $end
$var reg 1 " clk $end
$var reg 8 # d [7:0] $end
$var reg 1 $ en $end
$var reg 1 % rst $end
$scope module r $end
$var wire 1 " clk $end
$var wire 8 & d [7:0] $end
$var wire 1 $ en $end
$var wire 1 % rst $end
$var reg 8 ' q [7:0] $end
$upscope $end
$upscope $end
$enddefinitions $end
#0
$dumpvars
bx '
bx &
0%
1$
bx #
0"
bx !
$end
#10
1"
#20
0"
#30
1"
#40
0"
#50
b11111 !
b11111 '
1"
b11111 #
b11111 &
#60
0"
#70
1"
#80
0"
#90
1"
#100
0"
b1111111 #
b1111111 &
#110
b1111111 !
b1111111 '
1"
#120
0"
#130
1"
#140
0"
#150
1"
0$
#160
0"
#170
1"
#180
0"
#190
1"
#200
0"
b1100 #
b1100 &
#210
1"
#220
0"
#230
1"
#240
0"
#250
b0 !
b0 '
1"
1%
b1100100 #
b1100100 &
1$
#260
0"
#270
1"
#280
0"
#290
1"
#300
0"
0%
0$
