src/ecu/pc/pc.v
module pc
(
    input[15:0] ai,

    input clk, rst,

    //load and reset counter
    //increment to next instruction
    //count up both
    input lrc, ini, cub,

    //for address bus ports
    input oe,

    output reg[15:0] ao,
    output reg[2:0] is
);

    reg[15:0] ac = 0;
    reg[2:0] ic = 0;

    reg cv = 0;

    //for simulation purposes only
    initial
    begin
        ac = 16'h8000;
        ic = 3'b000;
    end

    always @(posedge clk)
    begin
        if (rst)
        begin
            ac <= 16'h8000;
            ic <= 3'b000;
        end

        else
        begin
            if (ic == 3'b111)
            begin
                ic <= 0;
                ac += 1;
            end

            //else if (ic == 3'b110 && )
            //begin


            if (lrc)
            begin
                ic <= 3'b000;
                ac <= ai;
            end

            else if (ini)
            begin
                ic <= 3'b000;
                ac += 1;
            end

            else if (cub)
            begin
                ic += 2;
                ac += 1;
            end

            else
                ic += 1;

            // TODO: verify address on { 0x8000 <= a <= 0xFFFF - 3 }
            //three is max extra instruction lengths



            //output address and step
            if (oe)
                ao <= ac;

            is <= ic;
        end
    end
endmodule

src/ecu/pc/pc_tb.v
`timescale 1ns / 100ps
`include "pc.v"

module pc_tb;
    reg clk = 0;
    reg rst = 0;

    reg[15:0] ai = 0;

    reg lrc = 0;
    reg ini = 0;
    reg cub = 0;

    reg oe = 0;

    wire[15:0] ao;
    wire[2:0] is;

always #1 clk = !clk;

initial $dumpfile("pc_tb.vcd");
initial $dumpvars(0, pc_tb);

pc ipc
(
    .ai(ai),
    .clk(clk),
    .rst(rst),
    .lrc(lrc),
    .ini(ini),
    .cub(cub),
    .oe(oe),
    .ao(ao),
    .is(is)
);

initial
begin
    #5 oe = 1;
    #5
    #5
    #5
    #5 ini = 1;
    #2 ini = 0;
    #5 ai = 16'h800A; lrc = 1;
    #2 lrc = 0;
    #5 cub = 1;
    #2 cub = 0;
    #2
    #2
    #2
    #2
    #2 oe = 0;
    #2
    #2
    #2 oe = 1;
    #5 rst = 1;
    #2 rst = 0;
    #5 $finish;
end

endmodule

src/ecu/pc/pc_tb.vcd
$date
	Wed Sep  7 16:48:52 2022
$end
$version
	Icarus Verilog
$end
$timescale
	100ps
$end
$scope module pc_tb $end
$var wire 3 ! is [2:0] $end
$var wire 16 " ao [15:0] $end
$var reg 16 # ai [15:0] $end
$var reg 1 $ clk $end
$var reg 1 % cub $end
$var reg 1 & ini $end
$var reg 1 ' lrc $end
$var reg 1 ( oe $end
$var reg 1 ) rst $end
$scope module ipc $end
$var wire 16 * ai [15:0] $end
$var wire 1 $ clk $end
$var wire 1 % cub $end
$var wire 1 & ini $end
$var wire 1 ' lrc $end
$var wire 1 ( oe $end
$var wire 1 ) rst $end
$var reg 16 + ac [15:0] $end
$var reg 16 , ao [15:0] $end
$var reg 1 - cv $end
$var reg 3 . ic [2:0] $end
$var reg 3 / is [2:0] $end
$upscope $end
$upscope $end
$enddefinitions $end
#0
$dumpvars
bx /
b0 .
0-
bx ,
b1000000000000000 +
b0 *
0)
0(
0'
0&
0%
0$
b0 #
bx "
bx !
$end
#10
b1 !
b1 /
b1 .
1$
#20
0$
#30
b10 !
b10 /
b10 .
1$
#40
0$
#50
b11 !
b11 /
b1000000000000000 "
b1000000000000000 ,
b11 .
1$
1(
#60
0$
#70
b100 !
b100 /
b100 .
1$
#80
0$
#90
b101 !
b101 /
b101 .
1$
#100
0$
#110
b110 !
b110 /
b110 .
1$
#120
0$
#130
b111 !
b111 /
b111 .
1$
#140
0$
#150
b0 !
b0 /
b1000000000000001 "
b1000000000000001 ,
b0 .
b1000000000000001 +
1$
#160
0$
#170
b1 !
b1 /
b1 .
1$
#180
0$
#190
b10 !
b10 /
b10 .
1$
#200
0$
#210
b11 !
b11 /
b11 .
1$
#220
0$
#230
b100 !
b100 /
b100 .
1$
#240
0$
#250
b1000000000000010 "
b1000000000000010 ,
b0 .
b1000000000000010 +
1$
1&
#260
0$
#270
b1 !
b1 /
b1 .
1$
0&
#280
0$
#290
b10 !
b10 /
b10 .
1$
#300
0$
#310
b11 !
b11 /
b11 .
1$
#320
0$
1'
b1000000000001010 #
b1000000000001010 *
#330
b1000000000001010 +
b0 .
1$
#340
0$
0'
#350
b1 !
b1 /
b1000000000001010 "
b1000000000001010 ,
b1 .
1$
#360
0$
#370
b10 !
b10 /
b10 .
1$
#380
0$
#390
b100 !
b100 /
b1000000000001011 "
b1000000000001011 ,
b1000000000001011 +
b100 .
1$
1%
#400
0$
#410
b101 !
b101 /
b101 .
1$
0%
#420
0$
#430
b110 !
b110 /
b110 .
1$
#440
0$
#450
b111 !
b111 /
b111 .
1$
#460
0$
#470
b0 !
b0 /
b1000000000001100 "
b1000000000001100 ,
b0 .
b1000000000001100 +
1$
#480
0$
#490
b1 !
b1 /
b1 .
1$
#500
0$
#510
b10 !
b10 /
b10 .
1$
0(
#520
0$
#530
b11 !
b11 /
b11 .
1$
#540
0$
#550
b100 !
b100 /
b100 .
1$
#560
0$
#570
b101 !
b101 /
b101 .
1$
1(
#580
0$
#590
b110 !
b110 /
b110 .
1$
#600
0$
#610
b111 !
b111 /
b111 .
1$
#620
0$
1)
#630
b0 .
b1000000000000000 +
1$
#640
0$
0)
#650
b1 !
b1 /
b1000000000000000 "
b1000000000000000 ,
b1 .
1$
#660
0$
#670
b10 !
b10 /
b10 .
1$
#680
0$
#690
b11 !
b11 /
b11 .
1$
