src/lsu/eau/eau.v
module eau
(
    input[7:0] d,
    
    input wl, wh,
    input clk, rst,

    input oe,

    output reg[15:0] q
);
    reg[15:0] tmp;

    initial 
    begin
        tmp <= 16'h0000;
    end

    always @(posedge clk)
    begin
        if (rst)
        begin
            tmp <= 16'h0000;

            if (oe)
                q <= tmp;
            else 
                q <= 16'bz;
        end

        else
        begin
            if (wl)
                tmp[7:0] <= d;

            else if (wh)
                tmp[15:8] <= d;

            if (oe)
                q <= tmp;

            else
                q <= 16'bz;
        end
    end

endmodule

src/lsu/eau/eau_tb.v
`timescale 1ns / 100ps
`include "eau.v"

module eau_tb;
    reg clk = 0, rst = 0;
    reg wl = 0, wh = 0;
    reg oe = 0;

    reg[7:0] d = 0;

    wire[15:0] q;

always #1 clk = !clk;

initial $dumpfile("eau_tb.vcd");
initial $dumpvars(0, eau_tb);

eau e
(
    .d(d),
    .clk(clk),
    .rst(rst),
    .wl(wl),
    .wh(wh),
    .oe(oe),
    .q(q)
);

initial
begin
    #5 d = 100; wl = 1; oe = 1;
    #5 d = 64; wl = 0; wh = 1;
    #5 wh = 0;
    #5 oe = 0;
    #5 oe = 1;
    #5 oe = 0;
    #1
    #5 d = 32; wh = 1;
    #5 wh = 0;
    #5 oe = 1;
    #5 rst = 1;
    #5
    #5 $finish;
end

endmodule

src/lsu/eau/eau_tb.vcd
$date
	Thu Sep  8 16:12:16 2022
$end
$version
	Icarus Verilog
$end
$timescale
	100ps
$end
$scope module eau_tb $end
$var wire 16 ! q [15:0] $end
$var reg 1 " clk $end
$var reg 8 # d [7:0] $end
$var reg 1 $ oe $end
$var reg 1 % rst $end
$var reg 1 & wh $end
$var reg 1 ' wl $end
$scope module e $end
$var wire 1 " clk $end
$var wire 8 ( d [7:0] $end
$var wire 1 $ oe $end
$var wire 1 % rst $end
$var wire 1 & wh $end
$var wire 1 ' wl $end
$var reg 16 ) q [15:0] $end
$var reg 16 * tmp [15:0] $end
$upscope $end
$upscope $end
$enddefinitions $end
#0
$dumpvars
b0 *
bx )
b0 (
0'
0&
0%
0$
b0 #
0"
bx !
$end
#10
bz !
bz )
1"
#20
0"
#30
1"
#40
0"
#50
b0 !
b0 )
b1100100 *
1"
1$
1'
b1100100 #
b1100100 (
#60
0"
#70
b1100100 !
b1100100 )
1"
#80
0"
#90
1"
#100
0"
1&
0'
b1000000 #
b1000000 (
#110
b100000001100100 *
1"
#120
0"
#130
b100000001100100 !
b100000001100100 )
1"
#140
0"
#150
1"
0&
#160
0"
#170
1"
#180
0"
#190
1"
#200
0"
0$
#210
bz !
bz )
1"
#220
0"
#230
1"
#240
0"
#250
b100000001100100 !
b100000001100100 )
1"
1$
#260
0"
#270
1"
#280
0"
#290
1"
#300
0"
0$
#310
bz !
bz )
1"
#320
0"
#330
1"
#340
0"
#350
1"
#360
0"
1&
b100000 #
b100000 (
#370
b10000001100100 *
1"
#380
0"
#390
1"
#400
0"
#410
1"
0&
#420
0"
#430
1"
#440
0"
#450
1"
#460
0"
1$
#470
b10000001100100 !
b10000001100100 )
1"
#480
0"
#490
1"
#500
0"
#510
b0 *
1"
1%
#520
0"
#530
b0 !
b0 )
1"
