src/alu/alu.v
module alu
(
    input[7:0] a, b, fi,
    
    input[6:0] op, 
    input clk, rst,

    output reg[7:0] d, fo
);
    reg[8:0] out = 0;
    reg[7:0] flags = 0;

    reg[8:0] ai, bi;
    reg signed[7:0] tmp;

    localparam CARRY = 0;

    initial
    begin
        out = 0;
        flags = 0;
    end

    always @(posedge clk)
    begin
        if (rst)
        begin
            out = 0;
            flags = 0;
        end

        else
        begin
            ai <= { 1'b0, a };
            bi <= { 1'b0, b };

            case (op)
                7'b0000001: //addition
                begin
                    out <= ai + bi + { 8'h00, fi[CARRY] };
                    flags[CARRY] <= out[8];
                end

                7'b0000010: //subtraction
                begin
                    out <= ai - bi - { 8'h00, fi[CARRY] };
                    flags[CARRY] <= out[8];
                end

                7'b0000100: //bitwise and
                begin
                    out <= ai & bi;
                end

                7'b0001000: //bitwise or
                begin
                    out <= ai | bi;
                end

                7'b0010000: //bitwise not
                begin
                    out <= ~ai;
                end

                7'b0100000: //left shift
                begin
                    out <= ai << bi;
                end

                7'b1000000: //right shift
                begin
                    out <= ai >> bi;
                end

                default: out <= 0;
            endcase

            flags[1] <= (out[7:0] == 0);
            tmp = out[7:0];
            flags[2] <= (tmp > 0);

            d <= out[7:0];
            fo <= flags;
        end
    end
endmodule

src/alu/alu_tb.v
`timescale 1ns / 100ps
`include "alu.v"

module alu_tb;
    reg[7:0] a = 0, b = 0, fi = 0;
    reg[6:0] op = 0;
    reg clk = 0, rst = 0;
    wire[7:0] d, fo;

always #1 clk = !clk;

initial $dumpfile("alu_tb.vcd");
initial $dumpvars(0, alu_tb);

alu alu
(
    .a(a),
    .b(b),
    .fi(fi),
    .op(op),
    .clk(clk),
    .rst(rst),
    .d(d),
    .fo(fo)
);

initial
begin
    #5 a = 1; b = 100; fi = 0; op = 0;
    #5 op = 1;
    #5 op = 2;
    #5 op = 3;
    #5 op = 4;
    #1
    #5 op = 8;
    #5 op = 16;
    #5 op = 32;
    #5 op = 64;
    #5 op = 65;
    #5 $finish;
end

endmodule

src/alu/alu_tb.vcd
$date
	Sun Sep 11 21:35:02 2022
$end
$version
	Icarus Verilog
$end
$timescale
	100ps
$end
$scope module alu_tb $end
$var wire 8 ! fo [7:0] $end
$var wire 8 " d [7:0] $end
$var reg 8 # a [7:0] $end
$var reg 8 $ b [7:0] $end
$var reg 1 % clk $end
$var reg 8 & fi [7:0] $end
$var reg 7 ' op [6:0] $end
$var reg 1 ( rst $end
$scope module alu $end
$var wire 8 ) a [7:0] $end
$var wire 8 * b [7:0] $end
$var wire 1 % clk $end
$var wire 8 + fi [7:0] $end
$var wire 7 , op [6:0] $end
$var wire 1 ( rst $end
$var reg 9 - ai [8:0] $end
$var reg 9 . bi [8:0] $end
$var reg 8 / d [7:0] $end
$var reg 8 0 flags [7:0] $end
$var reg 8 1 fo [7:0] $end
$var reg 9 2 out [8:0] $end
$var reg 8 3 tmp [7:0] $end
$upscope $end
$upscope $end
$enddefinitions $end
#0
$dumpvars
bx 3
b0 2
bx 1
b0 0
bx /
bx .
bx -
b0 ,
b0 +
b0 *
b0 )
0(
b0 '
b0 &
0%
b0 $
b0 #
bx "
bx !
$end
#10
b0 !
b0 1
b0 "
b0 /
b10 0
b0 .
b0 -
b0 3
1%
#20
0%
#30
b10 !
b10 1
1%
#40
0%
#50
b1100100 .
b1 -
1%
b1100100 $
b1100100 *
b1 #
b1 )
#60
0%
#70
1%
#80
0%
#90
1%
#100
0%
b1 '
b1 ,
#110
b1100101 2
1%
#120
0%
#130
b1100101 "
b1100101 /
b100 0
b1100101 3
1%
#140
0%
#150
b100 !
b100 1
b110011101 2
1%
b10 '
b10 ,
#160
0%
#170
b10011101 "
b10011101 /
b1 0
b10011101 3
1%
#180
0%
#190
b1 !
b1 1
1%
#200
0%
b11 '
b11 ,
#210
b0 2
1%
#220
0%
#230
b0 "
b0 /
b11 0
b0 3
1%
#240
0%
#250
b11 !
b11 1
1%
b100 '
b100 ,
#260
0%
#270
1%
#280
0%
#290
1%
#300
0%
#310
b1100101 2
1%
b1000 '
b1000 ,
#320
0%
#330
b1100101 "
b1100101 /
b101 0
b1100101 3
1%
#340
0%
#350
b101 !
b101 1
1%
#360
0%
b10000 '
b10000 ,
#370
b111111110 2
1%
#380
0%
#390
b11111110 "
b11111110 /
b1 0
b11111110 3
1%
#400
0%
#410
b1 !
b1 1
b0 2
1%
b100000 '
b100000 ,
#420
0%
#430
b0 "
b0 /
b11 0
b0 3
1%
#440
0%
#450
b11 !
b11 1
1%
#460
0%
b1000000 '
b1000000 ,
#470
1%
#480
0%
#490
1%
#500
0%
#510
1%
b1000001 '
b1000001 ,
