cpu/msc/reg/reg.v
module reg_std
(
    input[7:0] d, 
    
    input en,
    input clk,

    output reg[7:0] q
);
    always @(posedge clk)
    begin
        if (en)
            q <= d;
    end
endmodule

module reg_rst
(
    input[7:0] d,
    
    input we,
    input clk, rst,

    output reg[7:0] q
);
    initial
    begin
        q <= 8'b0;
    end

    always @(posedge clk)
    begin
        
        if (we && !rst)
            q <= d;
        else if (rst)
            q <= 8'b0;
    end
endmodule

cpu/rf/rf.v
`include "../msc/reg/reg.v"

module rf
(
    input[7:0] d,
    
    input ai, bi, ci, di, fi,
    input ao, bo, co, do, fo,

    input clk, rst,

    output[7:0] p, fq, fod
);

wire[7:0] ap, bp, cp, dp, fp;

reg_rst ar
(
    .d(d),
    .clk(clk),
    .rst(rst),
    .we(ai),
    .q(ap)
);

reg_rst br
(
    .d(d),
    .clk(clk),
    .rst(rst),
    .we(bi),
    .q(bp)
);

reg_rst cr
(
    .d(d),
    .clk(clk),
    .rst(rst),
    .we(ci),
    .q(cp)
);

reg_rst dr
(
    .d(d),
    .clk(clk),
    .rst(rst),
    .we(di),
    .q(dp)
);

reg_rst fr
(
    .d(d),
    .clk(clk),
    .rst(rst),
    .we(fi),
    .q(fp)
);

assign p = ao ? ap : 
           bo ? bp : 
           co ? cp : 
           do ? dp : 8'bz;

assign fq = fo ? fp : 8'bz;
assign fod = fp;

endmodule

cpu/rf/rf_tb.v
`timescale 1ns / 100ps
`include "rf.v"

module rf_tb;
    reg[7:0] d = 0;

    reg ai = 0, bi = 0, ci = 0, di = 0, fi = 0;
    reg ao = 0, bo = 0, co = 0, do = 0, fo = 0;

    reg clk = 0, rst = 0;

    wire[7:0] p, fq, fod;

always #1 clk = !clk;

initial $dumpfile("rf_tb.vcd");
initial $dumpvars(0, rf_tb);

rf r
(
    .d(d),
    .ai(ai),
    .bi(bi),
    .ci(ci),
    .di(di),
    .fi(fi),
    .ao(ao),
    .bo(bo),
    .co(co),
    .do(do),
    .fo(fo),
    .clk(clk),
    .rst(rst),
    .p(p),
    .fq(fq),
    .fod(fod)
);

initial
begin
    #4 rst = 1;
    #5 rst = 0;
    #5 d = 100; ai = 1; bi = 1; ao = 1;
    #5 d = 0; ai = 0; bi = 0; ao = 1;
    #5 ao = 0; bo = 1;
    #5 bo = 0; d = 64; ci = 1;
    #5 ci = 0; co = 1; d = 4; fi = 1;
    #5 d = 0; fi = 0; co = 0; fo = 1;
    #5 fo = 0;
    #1
    #5 rst = 1;
    #5 $finish;
end

endmodule

cpu/rf/rf_tb.vcd
$date
	Tue Sep 20 20:19:17 2022
$end
$version
	Icarus Verilog
$end
$timescale
	100ps
$end
$scope module rf_tb $end
$var wire 8 ! p [7:0] $end
$var wire 8 " fq [7:0] $end
$var wire 8 # fod [7:0] $end
$var reg 1 $ ai $end
$var reg 1 % ao $end
$var reg 1 & bi $end
$var reg 1 ' bo $end
$var reg 1 ( ci $end
$var reg 1 ) clk $end
$var reg 1 * co $end
$var reg 8 + d [7:0] $end
$var reg 1 , di $end
$var reg 1 - do $end
$var reg 1 . fi $end
$var reg 1 / fo $end
$var reg 1 0 rst $end
$scope module r $end
$var wire 1 $ ai $end
$var wire 1 % ao $end
$var wire 1 & bi $end
$var wire 1 ' bo $end
$var wire 1 ( ci $end
$var wire 1 ) clk $end
$var wire 1 * co $end
$var wire 8 1 d [7:0] $end
$var wire 1 , di $end
$var wire 1 - do $end
$var wire 1 . fi $end
$var wire 1 / fo $end
$var wire 8 2 fod [7:0] $end
$var wire 1 0 rst $end
$var wire 8 3 p [7:0] $end
$var wire 8 4 fq [7:0] $end
$var wire 8 5 fp [7:0] $end
$var wire 8 6 dp [7:0] $end
$var wire 8 7 cp [7:0] $end
$var wire 8 8 bp [7:0] $end
$var wire 8 9 ap [7:0] $end
$scope module ar $end
$var wire 1 ) clk $end
$var wire 8 : d [7:0] $end
$var wire 1 0 rst $end
$var wire 1 $ we $end
$var reg 8 ; q [7:0] $end
$upscope $end
$scope module br $end
$var wire 1 ) clk $end
$var wire 8 < d [7:0] $end
$var wire 1 0 rst $end
$var wire 1 & we $end
$var reg 8 = q [7:0] $end
$upscope $end
$scope module cr $end
$var wire 1 ) clk $end
$var wire 8 > d [7:0] $end
$var wire 1 0 rst $end
$var wire 1 ( we $end
$var reg 8 ? q [7:0] $end
$upscope $end
$scope module dr $end
$var wire 1 ) clk $end
$var wire 8 @ d [7:0] $end
$var wire 1 0 rst $end
$var wire 1 , we $end
$var reg 8 A q [7:0] $end
$upscope $end
$scope module fr $end
$var wire 1 ) clk $end
$var wire 8 B d [7:0] $end
$var wire 1 0 rst $end
$var wire 1 . we $end
$var reg 8 C q [7:0] $end
$upscope $end
$upscope $end
$upscope $end
$enddefinitions $end
#0
$dumpvars
b0 C
b0 B
b0 A
b0 @
b0 ?
b0 >
b0 =
b0 <
b0 ;
b0 :
b0 9
b0 8
b0 7
b0 6
b0 5
bz 4
bz 3
b0 2
b0 1
00
0/
0.
0-
0,
b0 +
0*
0)
0(
0'
0&
0%
0$
b0 #
bz "
bz !
$end
#10
1)
#20
0)
#30
1)
#40
0)
10
#50
1)
#60
0)
#70
1)
#80
0)
#90
1)
00
#100
0)
#110
1)
#120
0)
#130
1)
#140
b0 !
b0 3
0)
1%
1&
1$
b1100100 +
b1100100 1
b1100100 :
b1100100 <
b1100100 >
b1100100 @
b1100100 B
#150
b1100100 !
b1100100 3
b1100100 8
b1100100 =
b1100100 9
b1100100 ;
1)
#160
0)
#170
1)
#180
0)
#190
1)
0&
0$
b0 +
b0 1
b0 :
b0 <
b0 >
b0 @
b0 B
#200
0)
#210
1)
#220
0)
#230
1)
#240
b1100100 !
b1100100 3
0)
1'
0%
#250
1)
#260
0)
#270
1)
#280
0)
#290
b1000000 7
b1000000 ?
bz !
bz 3
1)
1(
b1000000 +
b1000000 1
b1000000 :
b1000000 <
b1000000 >
b1000000 @
b1000000 B
0'
#300
0)
#310
1)
#320
0)
#330
1)
#340
b1000000 !
b1000000 3
0)
1.
b100 +
b100 1
b100 :
b100 <
b100 >
b100 @
b100 B
1*
0(
#350
b100 #
b100 2
b100 5
b100 C
1)
#360
0)
#370
1)
#380
0)
#390
bz !
bz 3
b100 "
b100 4
1)
1/
0*
0.
b0 +
b0 1
b0 :
b0 <
b0 >
b0 @
b0 B
#400
0)
#410
1)
#420
0)
#430
1)
#440
bz "
bz 4
0)
0/
#450
1)
#460
0)
#470
1)
#480
0)
#490
1)
#500
0)
10
#510
b0 #
b0 2
b0 5
b0 C
b0 7
b0 ?
b0 8
b0 =
b0 9
b0 ;
1)
