src/msc/reg/reg.v
module reg_std
(
    input[7:0] d, 
    
    input en,
    input clk,

    output reg[7:0] q
);
    always @(posedge clk)
    begin
        if (en)
            q <= d;
    end
endmodule

module reg_rst
(
    input[7:0] d,
    
    input en,
    input clk, rst,

    output reg[7:0] q
);
    always @(posedge clk)
    begin
        if (en && !rst)
            q <= d;
        else if (rst)
            q <= 8'h00;
    end
endmodule

cpu/rf/rf.v
`include "../msc/reg/reg.v"

module rf
(
    input[7:0] d,
    
    input ai, bi, ci, di, fi,
    input ao, bo, co, do, fo,

    input clk, rst,

    output reg[7:0] p, fq, fod
);

wire[7:0] ap, bp, cp, dp, fp;

reg_rst ar
(
    .d(d),
    .clk(clk),
    .rst(rst),
    .en(ai),
    .q(ap)
);

reg_rst br
(
    .d(d),
    .clk(clk),
    .rst(rst),
    .en(bi),
    .q(bp)
);

reg_rst cr
(
    .d(d),
    .clk(clk),
    .rst(rst),
    .en(ci),
    .q(cp)
);

reg_rst dr
(
    .d(d),
    .clk(clk),
    .rst(rst),
    .en(di),
    .q(dp)
);

reg_rst fr
(
    .d(d),
    .clk(clk),
    .rst(rst),
    .en(fi),
    .q(fp)
);

wire want_output = (ao | bo | co | do | fo);

always @(posedge clk)
begin
    fod <= fp;

    if (!fo)
    begin
        if (want_output)
        begin
                 if (ao) p <= ap;
            else if (bo) p <= bp;
            else if (co) p <= cp;
            else if (do) p <= dp;
            else if (fo) p <= fp;
        end

        else
            p <= 8'bz;
            
        fq <= 8'bz;
    end

    else
    begin
        fq <= fp;
    end 
end

endmodule

cpu/rf/rf_tb.v
`timescale 1ns / 100ps
`include "rf.v"

module rf_tb;
    reg[7:0] d = 0;

    reg ai = 0, bi = 0, ci = 0, di = 0, fi = 0;
    reg ao = 0, bo = 0, co = 0, do = 0, fo = 0;

    reg clk = 0, rst = 0;

    wire[7:0] p, fq, fod;

always #1 clk = !clk;

initial $dumpfile("rf_tb.vcd");
initial $dumpvars(0, rf_tb);

rf r
(
    .d(d),
    .ai(ai),
    .bi(bi),
    .ci(ci),
    .di(di),
    .fi(fi),
    .ao(ao),
    .bo(bo),
    .co(co),
    .do(do),
    .fo(fo),
    .clk(clk),
    .rst(rst),
    .p(p),
    .fq(fq),
    .fod(fod)
);

initial
begin
    #5 d = 100; ai = 1; bi = 1;
    #5 d = 0; ai = 0; bi = 0; ao = 1;
    #5 ao = 0; bo = 1;
    #5 bo = 0; d = 64; ci = 1;
    #5 ci = 0; co = 1; d = 4; fi = 1;
    #5 d = 0; fi = 0; co = 0; fo = 1;
    #5 fo = 0;
    #5 rst = 1;
    #5 $finish;
end

endmodule

cpu/rf/rf_tb.vcd
$date
	Tue Sep 20 17:49:10 2022
$end
$version
	Icarus Verilog
$end
$timescale
	100ps
$end
$scope module rf_tb $end
$var wire 8 ! p [7:0] $end
$var wire 8 " fq [7:0] $end
$var wire 8 # fod [7:0] $end
$var reg 1 $ ai $end
$var reg 1 % ao $end
$var reg 1 & bi $end
$var reg 1 ' bo $end
$var reg 1 ( ci $end
$var reg 1 ) clk $end
$var reg 1 * co $end
$var reg 8 + d [7:0] $end
$var reg 1 , di $end
$var reg 1 - do $end
$var reg 1 . fi $end
$var reg 1 / fo $end
$var reg 1 0 rst $end
$scope module r $end
$var wire 1 $ ai $end
$var wire 1 % ao $end
$var wire 1 & bi $end
$var wire 1 ' bo $end
$var wire 1 ( ci $end
$var wire 1 ) clk $end
$var wire 1 * co $end
$var wire 8 1 d [7:0] $end
$var wire 1 , di $end
$var wire 1 - do $end
$var wire 1 . fi $end
$var wire 1 / fo $end
$var wire 1 0 rst $end
$var wire 1 2 want_output $end
$var wire 8 3 fp [7:0] $end
$var wire 8 4 dp [7:0] $end
$var wire 8 5 cp [7:0] $end
$var wire 8 6 bp [7:0] $end
$var wire 8 7 ap [7:0] $end
$var reg 8 8 fod [7:0] $end
$var reg 8 9 fq [7:0] $end
$var reg 8 : p [7:0] $end
$scope module ar $end
$var wire 1 ) clk $end
$var wire 8 ; d [7:0] $end
$var wire 1 $ en $end
$var wire 1 0 rst $end
$var reg 8 < q [7:0] $end
$upscope $end
$scope module br $end
$var wire 1 ) clk $end
$var wire 8 = d [7:0] $end
$var wire 1 & en $end
$var wire 1 0 rst $end
$var reg 8 > q [7:0] $end
$upscope $end
$scope module cr $end
$var wire 1 ) clk $end
$var wire 8 ? d [7:0] $end
$var wire 1 ( en $end
$var wire 1 0 rst $end
$var reg 8 @ q [7:0] $end
$upscope $end
$scope module dr $end
$var wire 1 ) clk $end
$var wire 8 A d [7:0] $end
$var wire 1 , en $end
$var wire 1 0 rst $end
$var reg 8 B q [7:0] $end
$upscope $end
$scope module fr $end
$var wire 1 ) clk $end
$var wire 8 C d [7:0] $end
$var wire 1 . en $end
$var wire 1 0 rst $end
$var reg 8 D q [7:0] $end
$upscope $end
$upscope $end
$upscope $end
$enddefinitions $end
#0
$dumpvars
bx D
b0 C
bx B
b0 A
bx @
b0 ?
bx >
b0 =
bx <
b0 ;
bx :
bx 9
bx 8
bx 7
bx 6
bx 5
bx 4
bx 3
02
b0 1
00
0/
0.
0-
0,
b0 +
0*
0)
0(
0'
0&
0%
0$
bx #
bx "
bx !
$end
#10
bz "
bz 9
bz !
bz :
1)
#20
0)
#30
1)
#40
0)
#50
b1100100 7
b1100100 <
b1100100 6
b1100100 >
1)
1&
1$
b1100100 +
b1100100 1
b1100100 ;
b1100100 =
b1100100 ?
b1100100 A
b1100100 C
#60
0)
#70
1)
#80
0)
#90
1)
#100
12
0)
1%
0&
0$
b0 +
b0 1
b0 ;
b0 =
b0 ?
b0 A
b0 C
#110
b1100100 !
b1100100 :
1)
#120
0)
#130
1)
#140
0)
#150
1)
1'
0%
#160
0)
#170
1)
#180
0)
#190
1)
#200
02
0)
1(
b1000000 +
b1000000 1
b1000000 ;
b1000000 =
b1000000 ?
b1000000 A
b1000000 C
0'
#210
b1000000 5
b1000000 @
bz !
bz :
1)
#220
0)
#230
1)
#240
0)
#250
b100 3
b100 D
12
1)
1.
b100 +
b100 1
b100 ;
b100 =
b100 ?
b100 A
b100 C
1*
0(
#260
0)
#270
b1000000 !
b1000000 :
b100 #
b100 8
1)
#280
0)
#290
1)
#300
0)
1/
0*
0.
b0 +
b0 1
b0 ;
b0 =
b0 ?
b0 A
b0 C
#310
b100 "
b100 9
1)
#320
0)
#330
1)
#340
0)
#350
bz "
bz 9
bz !
bz :
02
1)
0/
#360
0)
#370
1)
#380
0)
#390
1)
#400
0)
10
#410
b0 7
b0 <
b0 6
b0 >
b0 5
b0 @
b0 4
b0 B
b0 3
b0 D
1)
#420
0)
#430
b0 #
b0 8
1)
