src/util/register.v
module register(input[7:0] d, input clk, en, output reg[7:0] q);
    always @(posedge clk)
    begin
        if (en)
            q <= d;
    end
endmodule

module register_rst(input[7:0] d, input clk, rst, en, output reg[7:0] q);
    always @(posedge clk)
    begin
        if (en && !rst)
            q <= d;
        else if (rst)
            q <= 8'h00;
    end
endmodule

src/eau.v
`include "../util/register.v"


module Eau_D_A(input[7:0] d, input di, clk, rst, hs, ls, ao, output[15:0] a);
    wire[15:0] q;
    wire[7:0] p;
    assign p = d & { 8{ di } };

    register_rst rl
    (
        .d(p), 
        .clk(clk),
        .rst(rst), 
        .en(ls), 
        .q(q[7:0])
    );

    register_rst rh
    (
        .d(p),
        .clk(clk),
        .rst(rst),
        .en(hs),
        .q(q[15:8])
    );

    assign a = ao ? q : 16'bz;
endmodule


module Eau_A_D(input[15:0] a, input ai, clk, rst, hs, ls, do, output[7:0] d);
    wire[7:0] q = 0, l = 0, h = 0;

    assign q = (l & { 8{ ls } }) | (h & { 8{ hs } });

    wire[15:0] p;
    assign p = a & { 8{ ai } };

    register_rst rl
    (
        .d(p[7:0]), 
        .clk(clk),
        .rst(rst), 
        .en(ls), 
        .q(l)
    );

    register_rst rh
    (
        .d(p[15:8]),
        .clk(clk),
        .rst(rst),
        .en(hs),
        .q(h)
    );

    assign d = do ? (q) : (8'bz);
endmodule


module Eau(input[7:0] d, input[15:0] a, input ai, ao, di, do, hs, ls, clk, rst, output[7:0] dq, output[15:0] aq);
    Eau_D_A eau_da
    (
        .d(d),
        .di(di),
        .clk(clk),
        .rst(rst),
        .hs(hs),
        .ls(ls),
        .ao(ao),
        .a(aq)
    );

    Eau_A_D eau_ad
    (
        .a(a),
        .ai(ai),
        .clk(clk),
        .rst(rst),
        .hs(hs),
        .ls(ls),
        .do(do),
        .d(dq)
    );


endmodule

src/eau_tb.v
`timescale 1ns / 100ps
`include "eau.v"


module EauTestbench;
    reg clock = 0;

    reg[7:0] d = 0;
    reg[15:0] a = 0;
    reg ai = 0, ao = 0, di = 0, do = 0, hs = 0, ls = 0, rst = 0;
    
    wire[7:0] dq = 0;
    wire[15:0] aq = 0;


    always #1 clock = !clock;

    initial $dumpfile("eautestbench.vcd");
    initial $dumpvars(0, EauTestbench);

     Eau eau
     (
        .d(d),
        .a(a),
        .ai(ai),
        .ao(ao),
        .di(di),
        .do(do),
        .hs(hs),
        .ls(ls),
        .clk(clock),
        .rst(rst),
        .dq(dq),
        .aq(aq)
     );

    initial
    begin
        #5 d = 8'hF1; di = 1; ls = 1;
        #5 d = 8'h14; di = 1; ls = 0; hs = 1;
        #5 hs = 0; ao = 1;
        #5 rst = 1;
        #5 $finish;
    end

    //input[7:0] d, 
    //input[15:0] a, 
    //input ai, ao, di, do, hs, ls, clk, rst, 
    
    //output[7:0] dq, 
    //output[15:0] aq



endmodule

src/eautestbench.vcd
$date
	Sun Aug 28 01:00:04 2022
$end
$version
	Icarus Verilog
$end
$timescale
	100ps
$end
$scope module EauTestbench $end
$var wire 16 ! aq [15:0] $end
$var wire 8 " dq [7:0] $end
$var reg 16 # a [15:0] $end
$var reg 1 $ ai $end
$var reg 1 % ao $end
$var reg 1 & clock $end
$var reg 8 ' d [7:0] $end
$var reg 1 ( di $end
$var reg 1 ) do $end
$var reg 1 * hs $end
$var reg 1 + ls $end
$var reg 1 , rst $end
$scope module eau $end
$var wire 16 - a [15:0] $end
$var wire 1 $ ai $end
$var wire 1 % ao $end
$var wire 16 . aq [15:0] $end
$var wire 1 & clk $end
$var wire 8 / d [7:0] $end
$var wire 1 ( di $end
$var wire 1 ) do $end
$var wire 8 0 dq [7:0] $end
$var wire 1 * hs $end
$var wire 1 + ls $end
$var wire 1 , rst $end
$scope module eau_ad $end
$var wire 16 1 a [15:0] $end
$var wire 1 $ ai $end
$var wire 1 & clk $end
$var wire 8 2 d [7:0] $end
$var wire 1 ) do $end
$var wire 8 3 h [7:0] $end
$var wire 1 * hs $end
$var wire 8 4 l [7:0] $end
$var wire 1 + ls $end
$var wire 16 5 p [15:0] $end
$var wire 8 6 q [7:0] $end
$var wire 1 , rst $end
$scope module rh $end
$var wire 1 & clk $end
$var wire 8 7 d [7:0] $end
$var wire 1 * en $end
$var wire 1 , rst $end
$var reg 8 8 q [7:0] $end
$upscope $end
$scope module rl $end
$var wire 1 & clk $end
$var wire 8 9 d [7:0] $end
$var wire 1 + en $end
$var wire 1 , rst $end
$var reg 8 : q [7:0] $end
$upscope $end
$upscope $end
$scope module eau_da $end
$var wire 16 ; a [15:0] $end
$var wire 1 % ao $end
$var wire 1 & clk $end
$var wire 8 < d [7:0] $end
$var wire 1 ( di $end
$var wire 1 * hs $end
$var wire 1 + ls $end
$var wire 8 = p [7:0] $end
$var wire 1 , rst $end
$var wire 16 > q [15:0] $end
$scope module rh $end
$var wire 1 & clk $end
$var wire 8 ? d [7:0] $end
$var wire 1 * en $end
$var wire 1 , rst $end
$var reg 8 @ q [7:0] $end
$upscope $end
$scope module rl $end
$var wire 1 & clk $end
$var wire 8 A d [7:0] $end
$var wire 1 + en $end
$var wire 1 , rst $end
$var reg 8 B q [7:0] $end
$upscope $end
$upscope $end
$upscope $end
$upscope $end
$enddefinitions $end
#0
$dumpvars
bx B
b0 A
bx @
b0 ?
bx >
b0 =
b0 <
b0 ;
bx :
b0 9
bx 8
b0 7
b0 6
b0 5
bx 4
bx 3
b0 2
b0 1
b0 0
b0 /
b0 .
b0 -
0,
0+
0*
0)
0(
b0 '
0&
0%
0$
b0 #
b0 "
b0 !
$end
#10
1&
#20
0&
#30
1&
#40
0&
#50
bx 6
b11110001 =
b11110001 ?
b11110001 A
1&
1+
1(
b11110001 '
b11110001 /
b11110001 <
#60
b0 6
bx11110001 >
b11110001 B
b0 4
b0 :
0&
#70
1&
#80
0&
#90
1&
#100
bx 6
b10100 =
b10100 ?
b10100 A
0&
1*
0+
b10100 '
b10100 /
b10100 <
#110
1&
#120
b0 6
b0 3
b0 8
b1010011110001 >
b10100 @
0&
#130
1&
#140
0&
#150
b0x0x00xxxx000x !
b0x0x00xxxx000x .
b0x0x00xxxx000x ;
1&
1%
0*
#160
0&
#170
1&
#180
0&
#190
1&
#200
0&
1,
#210
1&
#220
b0 !
b0 .
b0 ;
b0 B
b0 >
b0 @
0&
